instant_rst/__init__.py
instant_rst/args.py
instant_rst/main.py
instant_rst/rst.py
instant_rst/server.py
instant_rst/settings.py
instant_rst/util.py
instant_rst/static/mars.css
instant_rst/static/molokai.css
instant_rst/static/rhythm.css
instant_rst/templates/404.html
instant_rst/templates/500.html
instant_rst/templates/index.html
instant_rst/templates/index.rst
instant_rst/templates/layout.html
instant_rst-0.9.9.1.data/scripts/instantRst
instant_rst-0.9.9.1.dist-info/METADATA
instant_rst-0.9.9.1.dist-info/WHEEL
instant_rst-0.9.9.1.dist-info/top_level.txt
instant_rst-0.9.9.1.dist-info/RECORD
